pcoetl/__init__.py
pcoetl/pco_etl.py
pcoetl/pcoetl.py
pcoetl-1.2.1.dist-info/METADATA
pcoetl-1.2.1.dist-info/WHEEL
pcoetl-1.2.1.dist-info/top_level.txt
pcoetl-1.2.1.dist-info/RECORD
