Metadata-Version: 2.1
Name: pcoetl
Version: 1.2.1
Summary: An ETL process for Planning Center
Author: Jacob Vandergriff
